{"ongoing_trials": {"tuner0": "0002"}, "hyperparameters": {"space": [{"class_name": "Choice", "config": {"name": "optimizer", "default": "adam", "conditions": [], "values": ["adam", "sgd", "rmsprop", "adagrad", "adadelta", "adamax", "nadam"], "ordered": false}}, {"class_name": "Choice", "config": {"name": "activation", "default": "relu", "conditions": [], "values": ["relu", "linear", "elu", "tanh", "sigmoid"], "ordered": false}}, {"class_name": "Int", "config": {"name": "first_units", "default": null, "conditions": [], "min_value": 8, "max_value": 64, "step": 8, "sampling": "linear"}}, {"class_name": "Int", "config": {"name": "num_layers", "default": null, "conditions": [], "min_value": 1, "max_value": 3, "step": 1, "sampling": "linear"}}, {"class_name": "Int", "config": {"name": "layer_0_units", "default": null, "conditions": [], "min_value": 8, "max_value": 64, "step": 8, "sampling": "linear"}}, {"class_name": "Int", "config": {"name": "layer_1_units", "default": null, "conditions": [], "min_value": 8, "max_value": 64, "step": 8, "sampling": "linear"}}, {"class_name": "Int", "config": {"name": "layer_2_units", "default": null, "conditions": [], "min_value": 8, "max_value": 64, "step": 8, "sampling": "linear"}}], "values": {"optimizer": "adam", "activation": "relu", "first_units": 8, "num_layers": 1, "layer_0_units": 8, "layer_1_units": 8, "layer_2_units": 8}}, "start_order": ["0000", "0001", "0002"], "end_order": ["0000", "0001"], "run_times": {"0000": 1, "0001": 1}, "retry_queue": [], "seed": 2344, "seed_state": 2361, "tried_so_far": ["e8f07348df10890eb32a3fc9c68a4f71", "45a1c3e104b2d8d7038ecdea691625c3", "e0ada621f76c9e19107dc7017876deef"], "id_to_hash": {"0000": "e0ada621f76c9e19107dc7017876deef", "0001": "45a1c3e104b2d8d7038ecdea691625c3", "0002": "e8f07348df10890eb32a3fc9c68a4f71"}, "display": {"search_start": "2024-06-06T18:33:17.020452", "trial_start": {"0000": "2024-06-06T18:33:17.020452", "0001": "2024-06-06T18:33:18.031565"}, "trial_number": {"0000": 1, "0001": 2}}, "hyperband_iterations": 2, "max_epochs": 50, "min_epochs": 1, "factor": 3, "brackets": [{"bracket_num": 3, "rounds": [[{"past_id": null, "id": "0000"}, {"past_id": null, "id": "0001"}, {"past_id": null, "id": "0002"}], [], [], []]}], "current_bracket": 3, "current_iteration": 0}